increase/__init__.py
increase/_base_client.py
increase/_client.py
increase/_compat.py
increase/_constants.py
increase/_exceptions.py
increase/_files.py
increase/_models.py
increase/_qs.py
increase/_resource.py
increase/_response.py
increase/_streaming.py
increase/_types.py
increase/_version.py
increase/pagination.py
increase/py.typed
increase/_utils/__init__.py
increase/_utils/_compat.py
increase/_utils/_datetime_parse.py
increase/_utils/_logs.py
increase/_utils/_proxy.py
increase/_utils/_reflection.py
increase/_utils/_resources_proxy.py
increase/_utils/_streams.py
increase/_utils/_sync.py
increase/_utils/_transform.py
increase/_utils/_typing.py
increase/_utils/_utils.py
increase/lib/.keep
increase/resources/__init__.py
increase/resources/account_numbers.py
increase/resources/account_statements.py
increase/resources/account_transfers.py
increase/resources/accounts.py
increase/resources/ach_prenotifications.py
increase/resources/ach_transfers.py
increase/resources/bookkeeping_accounts.py
increase/resources/bookkeeping_entries.py
increase/resources/bookkeeping_entry_sets.py
increase/resources/card_disputes.py
increase/resources/card_payments.py
increase/resources/card_purchase_supplements.py
increase/resources/card_push_transfers.py
increase/resources/card_tokens.py
increase/resources/card_validations.py
increase/resources/cards.py
increase/resources/check_deposits.py
increase/resources/check_transfers.py
increase/resources/declined_transactions.py
increase/resources/digital_card_profiles.py
increase/resources/digital_wallet_tokens.py
increase/resources/entities.py
increase/resources/event_subscriptions.py
increase/resources/events.py
increase/resources/exports.py
increase/resources/external_accounts.py
increase/resources/fednow_transfers.py
increase/resources/file_links.py
increase/resources/files.py
increase/resources/groups.py
increase/resources/inbound_ach_transfers.py
increase/resources/inbound_check_deposits.py
increase/resources/inbound_fednow_transfers.py
increase-0.423.0.dist-info/METADATA
increase-0.423.0.dist-info/WHEEL
increase-0.423.0.dist-info/licenses/LICENSE
increase-0.423.0.dist-info/RECORD
